{
  "id": "3669610",
  "name": "mi",
  "font_family": "iconfont",
  "css_prefix_text": "icon-",
  "description": "",
  "glyphs": [
    {
      "icon_id": "577362",
      "name": "时钟",
      "font_class": "shizhong",
      "unicode": "e74f",
      "unicode_decimal": 59215
    },
    {
      "icon_id": "5387978",
      "name": "资金循环_o",
      "font_class": "zijinxunhuan_o",
      "unicode": "eba6",
      "unicode_decimal": 60326
    },
    {
      "icon_id": "6528436",
      "name": "SD卡",
      "font_class": "SDqia",
      "unicode": "e649",
      "unicode_decimal": 58953
    },
    {
      "icon_id": "7594076",
      "name": "24gl-repeatInfinite",
      "font_class": "24gl-repeatInfinite",
      "unicode": "ea74",
      "unicode_decimal": 60020
    },
    {
      "icon_id": "13106266",
      "name": "建筑建材",
      "font_class": "jianzhujiancai",
      "unicode": "e60b",
      "unicode_decimal": 58891
    },
    {
      "icon_id": "15323496",
      "name": "F_round_字母f",
      "font_class": "F_round",
      "unicode": "e632",
      "unicode_decimal": 58930
    },
    {
      "icon_id": "1306",
      "name": "购物车空",
      "font_class": "gouwuchekong",
      "unicode": "e600",
      "unicode_decimal": 58880
    },
    {
      "icon_id": "490459",
      "name": "phone_iphone",
      "font_class": "phoneiphone",
      "unicode": "ec93",
      "unicode_decimal": 60563
    },
    {
      "icon_id": "579741",
      "name": "用户",
      "font_class": "yonghu",
      "unicode": "e788",
      "unicode_decimal": 59272
    },
    {
      "icon_id": "880429",
      "name": "扳手",
      "font_class": "editor2",
      "unicode": "e62e",
      "unicode_decimal": 58926
    },
    {
      "icon_id": "2674476",
      "name": "客服",
      "font_class": "kefu",
      "unicode": "e625",
      "unicode_decimal": 58917
    }
  ]
}
